setup.py
Topsis_SaiLohitaksh_102017090.egg-info/PKG-INFO
Topsis_SaiLohitaksh_102017090.egg-info/SOURCES.txt
Topsis_SaiLohitaksh_102017090.egg-info/dependency_links.txt
Topsis_SaiLohitaksh_102017090.egg-info/requires.txt
Topsis_SaiLohitaksh_102017090.egg-info/top_level.txt
topsis/__init__.py
topsis/topsis.py