Metadata-Version: 2.1
Name: Topsis-SaiLohitaksh-102017090
Version: 1.0
Summary: Python implementation of the Technique for Order of Preference by Similarity to Ideal Solution (TOPSIS)
Home-page: UNKNOWN
Author: Sai Lohitaksh
License: UNKNOWN
Platform: UNKNOWN
